exconsole/__init__.py
exconsole/console.py
python_exconsole-0.1.5.dist-info/metadata.json
python_exconsole-0.1.5.dist-info/METADATA
python_exconsole-0.1.5.dist-info/top_level.txt
python_exconsole-0.1.5.dist-info/DESCRIPTION.rst
python_exconsole-0.1.5.dist-info/WHEEL
python_exconsole-0.1.5.dist-info/RECORD
