Metadata-Version: 2.0
Name: python-exconsole
Version: 0.1.5
Summary: Emergency/postmortem Python console
Home-page: https://github.com/Eugeny/exconsole
Author: Eugene Pankov
Author-email: e@ajenti.org
License: UNKNOWN
Platform: UNKNOWN
